corebases/__init__.py
corebases/backends/__init__.py
corebases/backends/asyncpg.py
corebases/core.py
corebases/interface.py
corebases/py.typed
corebases-0.2.1.dist-info/LICENSE.md
corebases-0.2.1.dist-info/WHEEL
corebases-0.2.1.dist-info/METADATA
corebases-0.2.1.dist-info/RECORD
