Metadata-Version: 2.1
Name: corebases
Version: 0.2.1
Summary: Full power of *asyncpg* with user friendly api of *sqlalchemy.core*
Home-page: https://github.com/zueve/corebases
License: BSD
Author: Evgeny Zuev
Author-email: zueves@gmail.com
Requires-Python: >=3.7,<4.0
Classifier: Development Status :: 3 - Alpha
Classifier: Intended Audience :: Developers
Classifier: License :: OSI Approved :: BSD License
Classifier: License :: Other/Proprietary License
Classifier: Operating System :: OS Independent
Classifier: Programming Language :: Python :: 3
Classifier: Programming Language :: Python :: 3.7
Classifier: Programming Language :: Python :: 3.8
Classifier: Programming Language :: Python :: 3.9
Classifier: Programming Language :: Python :: 3.10
Classifier: Programming Language :: Python :: 3.11
Classifier: Programming Language :: Python :: 3
Classifier: Programming Language :: Python :: 3 :: Only
Classifier: Programming Language :: Python :: 3.10
Classifier: Programming Language :: Python :: 3.7
Classifier: Programming Language :: Python :: 3.8
Classifier: Programming Language :: Python :: 3.9
Requires-Dist: SQLAlchemy
Requires-Dist: asyncpg
Project-URL: Documentation, https://github.com/zueve/corebases
Project-URL: Repository, https://github.com/zueve/corebases
